mitol_django_digital_credentials-2023.12.19-py3.8-nspkg.pth
mitol/digitalcredentials/CHANGELOG.md
mitol/digitalcredentials/README.md
mitol/digitalcredentials/__init__.py
mitol/digitalcredentials/admin.py
mitol/digitalcredentials/apps.py
mitol/digitalcredentials/backend.py
mitol/digitalcredentials/factories.py
mitol/digitalcredentials/mixins.py
mitol/digitalcredentials/models.py
mitol/digitalcredentials/py.typed
mitol/digitalcredentials/requests_utils.py
mitol/digitalcredentials/serializers.py
mitol/digitalcredentials/settings.py
mitol/digitalcredentials/urls.py
mitol/digitalcredentials/views.py
mitol/digitalcredentials/migrations/0001_add_digital_credentials_models.py
mitol/digitalcredentials/migrations/0002_rename_courseware_to_credentialed.py
mitol/digitalcredentials/migrations/__init__.py
mitol_django_digital_credentials-2023.12.19.dist-info/METADATA
mitol_django_digital_credentials-2023.12.19.dist-info/WHEEL
mitol_django_digital_credentials-2023.12.19.dist-info/namespace_packages.txt
mitol_django_digital_credentials-2023.12.19.dist-info/top_level.txt
mitol_django_digital_credentials-2023.12.19.dist-info/zip-safe
mitol_django_digital_credentials-2023.12.19.dist-info/RECORD
