Metadata-Version: 2.1
Name: mitol-django-digital-credentials
Version: 2023.12.19
Summary: Django application to support digital credentials
License: BSD 3-Clause License
Classifier: Natural Language :: English
Classifier: Operating System :: OS Independent
Classifier: Programming Language :: Python
Classifier: Programming Language :: Python :: 3.6
Classifier: Programming Language :: Python :: 3.7
Classifier: Programming Language :: Python :: 3.8
Requires-Python: >=3.8
Requires-Dist: django-oauth-toolkit (>=1.3.3)
Requires-Dist: django (>=3.0)
Requires-Dist: djangorestframework (>=3.0.0)
Requires-Dist: factory-boy (~=3.2)
Requires-Dist: mitol-django-common
Requires-Dist: requests (>=2.20.0)
